donguk777_cmd/__init__.py
donguk777_cmd/cmd.py
DONGUK777_cmd-0.1.1.dist-info/METADATA
DONGUK777_cmd-0.1.1.dist-info/WHEEL
DONGUK777_cmd-0.1.1.dist-info/entry_points.txt
DONGUK777_cmd-0.1.1.dist-info/top_level.txt
DONGUK777_cmd-0.1.1.dist-info/RECORD
