Metadata-Version: 2.1
Name: DONGUK777_cmd
Version: 0.1.1
Summary: Default template for PDM package
Author-email: DONGUK777 <kimdongyork@gmail.com>
License: MIT
Requires-Python: >=3.9
